miniirc_matrix.py
miniirc_matrix-0.0.13.dist-info/LICENSE.md
miniirc_matrix-0.0.13.dist-info/METADATA
miniirc_matrix-0.0.13.dist-info/WHEEL
miniirc_matrix-0.0.13.dist-info/top_level.txt
miniirc_matrix-0.0.13.dist-info/RECORD
