Metadata-Version: 2.1
Name: miniirc_matrix
Version: 0.0.13
Summary: A Matrix wrapper for miniirc.
Author: luk3yx
License: MIT
Classifier: Intended Audience :: Developers
Classifier: Development Status :: 4 - Beta
Classifier: License :: OSI Approved :: MIT License
Classifier: Operating System :: OS Independent
Classifier: Programming Language :: Python :: 3
Classifier: Topic :: Software Development :: Libraries
Requires-Python: >=3.8
License-File: LICENSE.md
Requires-Dist: requests<3,>=2.22.0
Requires-Dist: miniirc<2,>=1.8.0
